Workbook

Sheet Project Summary
B2: Project Name : | C2: Majorda Villa | F2: PROJECT SUMMARY
B3: Client : | C3: Mr. Sanjay Rao
B4: Date : | C4: ='03-Work Order Tracker'!C4 -> 46026
B6: CODE | C6: Description | D6: Budget | E6: WO Value | F6: % Progress | G6: Payment Value
B7: ='Code-Categories'!B3 -> CIV | C7: ='Code-Categories'!C3 -> Civil Works | D7: ='Baseline Budget'!C19 -> 15000000 | E7: {='03-Work Order Tracker'!N7:N20} -> 10107426 | F7: {='02-Weekly Progress Report'!M7:M20} -> 0.51 | G7: {='04-Payment Certificate Tracker'!L7:L20} -> 1535000
B8: ='Code-Categories'!B4 -> PLB | C8: ='Code-Categories'!C4 -> Plumbing Works | E8: 0 | F8: 0 | G8: 0
B9: ='Code-Categories'!B5 -> ELC | C9: ='Code-Categories'!C5 -> Electrical Works | E9: 13530 | F9: 1 | G9: 13530
B10: ='Code-Categories'!B6 -> DWG | C10: ='Code-Categories'!C6 -> Doors, Windows & Glazing | E10: 0 | F10: 0 | G10: 0
B11: ='Code-Categories'!B7 -> SWP | C11: ='Code-Categories'!C7 -> Swimming Pool Works | E11: 0 | F11: 0 | G11: 0
B12: ='Code-Categories'!B8 -> HVC | C12: ='Code-Categories'!C8 -> HVAC / Air Conditioning | E12: 0 | F12: 0 | G12: 0
B13: ='Code-Categories'!B9 -> FIN | C13: ='Code-Categories'!C9 -> Finishing Works | E13: 0 | F13: 0 | G13: 0
B14: ='Code-Categories'!B10 -> LAN | C14: ='Code-Categories'!C10 -> Landscapping & External Works | E14: 0 | F14: 0 | G14: 0
B15: ='Code-Categories'!B11 -> FAB | C15: ='Code-Categories'!C11 -> Metal & Steel Fabrication | E15: 0 | F15: 0 | G15: 0
B16: ='Code-Categories'!B12 -> CSA | C16: ='Code-Categories'!C12 -> Client Supplied Assets | E16: 0 | F16: 0 | G16: 0
B17: ='Code-Categories'!B13 -> PRF | C17: ='Code-Categories'!C13 -> Professional Fees | E17: 14000 | F17: 1 | G17: 296520
B18: ='Code-Categories'!B14 -> STC | C18: ='Code-Categories'!C14 -> Approvals & Statutory Charges | E18: 0 | F18: 0 | G18: 0
B19: ='Code-Categories'!B15 -> PTC | C19: ='Code-Categories'!C15 -> Petty Cash / Running Expenses | E19: 0 | F19: 0 | G19: 0
B20: ='Code-Categories'!B16 -> CON | C20: ='Code-Categories'!C16 -> Contingency | E20: 0 | F20: 0 | G20: 0

Sheet 01-Task List
B2: Project Name : | C2: Majorda Villa | E2: PROJECT TASK LIST
B3: Client : | C3: Mr. Sanjay Rao
B4: Date : | C4: 46104
B6: Sr No | C6: OPEN Task Description | D6: Action By | E6: Deadline | F6: Status / Notes
B7: 1 | C7: SWall beam to be included in render. | D7: Omkar/Rajesh | E7: 46108
B8: 2 | C8: Column or stubbed steel on NW side got floating roof to be in rcc clarity. | D8: Omkar/Rajesh | E8: 46108
B9: 3 | C9: Jali wall material? | D9: Omkar/Rajesh | E9: 46108
B10: 4 | C10: Ventilator on seast room bay window in the east-facing room. (Suggestion if this is doable and look good) | D10: Omkar/Rajesh | E10: 46108
B11: 5 | C11: Cantilever extension to 4 ft into the setback to be checked with PMC. | D11: Amit | E11: 46108 | F11: Pls provide with section drawing to highlight this area, will check onsite and revert.
B12: 6 | C12: Shingles and material on the roof for render and south-side solar panels. | D12: Omkar/Rajesh | E12: 46108
B13: 7 | C13: POV for Terrace fireplace. | D13: Omkar/Rajesh | E13: 46108
B14: 8 | C14: south side FF opening for rooms does not match with the floor plan. ( Need some clarity) | D14: Omkar/Rajesh | E14: 46108
B15: 9 | C15: NW room sky roof POV. | D15: Omkar/Rajesh | E15: 46108
B16: 10 | C16: Laterite vs. terracotta brick cladding material mix. | D16: Omkar/Rajesh | E16: 46108
B17: 11 | C17: Can we obtain specific massing or design details for the entrance door, if possible? | D17: Omkar/Rajesh | E17: 46108
B18: 12 | C18: Installing CCTV Cameras onsite | D18: Amit | E18: 46106
B19: 13 | C19: Swimming Pool services drawings to be issued. | D19: Santosh | E19: 46106
B20: 14 | C20: Pool Vendor onboarding | D20: Amit | E20: 46111 | F20: After confirmation of swimming pool services drawings
B21: 15 | C21: Electrical Specs/BOQ to be issued | D21: MEP | E21: 46111
B22: 16 | C22: Electrican Vendor Onboarding | D22: Amit | E22: 46122 | F22: After receipt of Electrical BOQ
B23: 17 | C23: Plumbing Specs/BOQ to be Issued | D23: MEP | E23: 46111
B24: 18 | C24: Plumbing Vendor Onboarding | D24: Amit | E24: 46122 | F24: After receipt of Plumbing BOQ
B25: 19 | C25: Door Window Schedule to be issued | D25: Omkar/Rajesh | E25: 46111
B26: 20 | C26: Car Park area Entry from North East, clashing with onsite electrical post, need final decision to move forward | D26: Omkar/Rajesh | E26: 46111
B31: Sr No | C31: COMPLETED Task Description | D31: Action By | E31: Deadline | F31: Status / Notes
B32: 1 | C32: E-mail Confirmation to Structural | D32: Omkar / Rajesh | E32: 45662 | F32: Critical, to be completed
B33: 2 | C33: Footing & Steel Drawings | D33: Paresh | E33: =E7+4 -> 46112 | F33: Mamta will take 3 days to complete steel & footing drawings if no changes.
B34: 3 | C34: Civil BOQ | D34: Amit | E34: =E33+4 -> 46116 | F34: Contract ready BOQ will only be ready after receipt of complete structural drawings including footing & steel
B35: 4 | C35: Civil Contract Award, Advance to be paid | D35: Amit | E35: =E34+3 -> 46119 | F35: PS Engrs, SS Construction, Madhav Patra (Team available for mid Jan)
B36: 5 | C36: Civil Works to be started onsite | D36: Amit | E36: =E35+3 -> 46122 | F36: Vendor to be confirmed.
B37: 6 | C37: MEP Meeting for Levels, Septic & Sump Location | D37: Amit | E37: =E33+1 -> 46113 | F37: After receipt of Footing drawings.
B38: 7 | C38: MEP BOQ & Specs to be prepared | D38: MEP Consultant | E38: =E37+5 -> 46118 | F38: Needed once we reach plinth filling.
B39: 8 | C39: Electrical Contract Award, Advance to be paid | D39: Amit | E39: =E38+6 -> 46124 | F39: Electrical contractor to be onboard before plinth filling.

Sheet 02-Weekly Progress Report
B2: Project Name : | C2: Majorda Villa | H2: PROJECT PROGRESS REPORT
B3: Client : | C3: Mr. Sanjay Rao
B4: Date : | C4: ='03-Work Order Tracker'!C4 -> 46026
B6: CODE | C6: Vendor | D6: WO Refn | E6: WO Issued Date | F6: Start Date | G6: End Date | H6: % Completed | I6: Comments | K6: CODE | M6: Average Value
B7: ='03-Work Order Tracker'!B7 -> CIV | C7: ='03-Work Order Tracker'!C7 -> SS Construction | D7: ='03-Work Order Tracker'!D7 -> TAC_WO_25_003 | E7: ='03-Work Order Tracker'!E7 -> 46003 | F7: ='03-Work Order Tracker'!I7 -> 46005 | G7: ='03-Work Order Tracker'!J7 -> 46011 | H7: 1 | I7: Activity Completed | K7: ='Code-Categories'!B3 -> CIV | L7: ='Code-Categories'!C3 -> Civil Works | M7: =AVERAGEIF($B$7:$B$64,K7,$H$7:$H$64) -> 0.51
B8: ='03-Work Order Tracker'!B8 -> ELC | C8: ='03-Work Order Tracker'!C8 -> Suraj Electrician | D8: ='03-Work Order Tracker'!D8 -> TAC_WO_25_004 | E8: ='03-Work Order Tracker'!E8 -> 46014 | F8: ='03-Work Order Tracker'!I8 -> 46014 | G8: ='03-Work Order Tracker'!J8 -> 46019 | H8: 1 | I8: Activity Completed | K8: ='Code-Categories'!B4 -> PLB | L8: ='Code-Categories'!C4 -> Plumbing Works | M8: =SUMIF($B$7:$B$38,K8,$H$7:$H$38) -> 0
B9: CIV | C9: Rajesh Construction | D9: TAC_WO_25_005 | E9: 46060 | F9: 46070 | G9: 46371 | H9: 0.02 | K9: ='Code-Categories'!B5 -> ELC | L9: ='Code-Categories'!C5 -> Electrical Works | M9: =SUMIF($B$7:$B$38,K9,$H$7:$H$38) -> 1
B10: PRF | C10: CDSP Global | D10: TAC_WO_25_006 | E10: 46082 | F10: 46071 | G10: 46071 | H10: 1 | I10: Activity Completed | K10: ='Code-Categories'!B6 -> DWG | L10: ='Code-Categories'!C6 -> Doors, Windows & Glazing | M10: =SUMIF($B$7:$B$38,K10,$H$7:$H$38) -> 0
K11: ='Code-Categories'!B7 -> SWP | L11: ='Code-Categories'!C7 -> Swimming Pool Works | M11: =SUMIF($B$7:$B$38,K11,$H$7:$H$38) -> 0
K12: ='Code-Categories'!B8 -> HVC | L12: ='Code-Categories'!C8 -> HVAC / Air Conditioning | M12: =SUMIF($B$7:$B$38,K12,$H$7:$H$38) -> 0
K13: ='Code-Categories'!B9 -> FIN | L13: ='Code-Categories'!C9 -> Finishing Works | M13: =SUMIF($B$7:$B$38,K13,$H$7:$H$38) -> 0
K14: ='Code-Categories'!B10 -> LAN | L14: ='Code-Categories'!C10 -> Landscapping & External Works | M14: =SUMIF($B$7:$B$38,K14,$H$7:$H$38) -> 0
K15: ='Code-Categories'!B11 -> FAB | L15: ='Code-Categories'!C11 -> Metal & Steel Fabrication | M15: =SUMIF($B$7:$B$38,K15,$H$7:$H$38) -> 0
K16: ='Code-Categories'!B12 -> CSA | L16: ='Code-Categories'!C12 -> Client Supplied Assets | M16: =SUMIF($B$7:$B$38,K16,$H$7:$H$38) -> 0
K17: ='Code-Categories'!B13 -> PRF | L17: ='Code-Categories'!C13 -> Professional Fees | M17: =SUMIF($B$7:$B$38,K17,$H$7:$H$38) -> 1
K18: ='Code-Categories'!B14 -> STC | L18: ='Code-Categories'!C14 -> Approvals & Statutory Charges | M18: =SUMIF($B$7:$B$38,K18,$H$7:$H$38) -> 0
K19: ='Code-Categories'!B15 -> PTC | L19: ='Code-Categories'!C15 -> Petty Cash / Running Expenses | M19: =SUMIF($B$7:$B$38,K19,$H$7:$H$38) -> 0
K20: ='Code-Categories'!B16 -> CON | L20: ='Code-Categories'!C16 -> Contingency | M20: =SUMIF($B$7:$B$38,K20,$H$7:$H$38) -> 0

Sheet 03-Work Order Tracker
B2: Project Name : | C2: Majorda Villa | H2: WORK ORDER TRACKER
B3: Client : | C3: Mr. Sanjay Rao
B4: Date : | C4: 46026
B6: CODE | C6: Vendor | D6: WO Refn | E6: WO Issued Date | F6: WO Value | G6: GST | H6: Retention Value | I6: Start Date | J6: End Date | L6: CODE | N6: Total Value
B7: CIV | C7: SS Construction | D7: TAC_WO_25_003 | E7: 46003 | F7: 35000 | G7: 0 | H7: 0 | I7: 46005 | J7: 46011 | L7: ='Code-Categories'!B3 -> CIV | M7: ='Code-Categories'!C3 -> Civil Works | N7: =SUMIF($B$7:$B$38,L7,$F$7:$F$38) -> 10107426
B8: ELC | C8: Suraj Electrician | D8: TAC_WO_25_004 | E8: 46014 | F8: 13530 | G8: 0 | H8: 0 | I8: 46014 | J8: 46019 | L8: ='Code-Categories'!B4 -> PLB | M8: ='Code-Categories'!C4 -> Plumbing Works | N8: =SUMIF($B$7:$B$38,L8,$F$7:$F$38) -> 0
B9: CIV | C9: Rajesh Construction | D9: TAC_WO_25_005 | E9: 46060 | F9: 10072426 | G9: =F9*18% -> 1813036.7 | H9: =F9*5% -> 503621.3 | I9: 46070 | J9: 46371 | L9: ='Code-Categories'!B5 -> ELC | M9: ='Code-Categories'!C5 -> Electrical Works | N9: =SUMIF($B$7:$B$38,L9,$F$7:$F$38) -> 13530
B10: PRF | C10: CDSP Global | D10: TAC_WO_25_006 | E10: 46082 | F10: 14000 | G10: =F10*18% -> 2520 | H10: 0 | I10: 46071 | J10: 46071 | L10: ='Code-Categories'!B6 -> DWG | M10: ='Code-Categories'!C6 -> Doors, Windows & Glazing | N10: =SUMIF($B$7:$B$38,L10,$F$7:$F$38) -> 0
L11: ='Code-Categories'!B7 -> SWP | M11: ='Code-Categories'!C7 -> Swimming Pool Works | N11: =SUMIF($B$7:$B$38,L11,$F$7:$F$38) -> 0
L12: ='Code-Categories'!B8 -> HVC | M12: ='Code-Categories'!C8 -> HVAC / Air Conditioning | N12: =SUMIF($B$7:$B$38,L12,$F$7:$F$38) -> 0
L13: ='Code-Categories'!B9 -> FIN | M13: ='Code-Categories'!C9 -> Finishing Works | N13: =SUMIF($B$7:$B$38,L13,$F$7:$F$38) -> 0
L14: ='Code-Categories'!B10 -> LAN | M14: ='Code-Categories'!C10 -> Landscapping & External Works | N14: =SUMIF($B$7:$B$38,L14,$F$7:$F$38) -> 0
L15: ='Code-Categories'!B11 -> FAB | M15: ='Code-Categories'!C11 -> Metal & Steel Fabrication | N15: =SUMIF($B$7:$B$38,L15,$F$7:$F$38) -> 0
L16: ='Code-Categories'!B12 -> CSA | M16: ='Code-Categories'!C12 -> Client Supplied Assets | N16: =SUMIF($B$7:$B$38,L16,$F$7:$F$38) -> 0
L17: ='Code-Categories'!B13 -> PRF | M17: ='Code-Categories'!C13 -> Professional Fees | N17: =SUMIF($B$7:$B$38,L17,$F$7:$F$38) -> 14000
L18: ='Code-Categories'!B14 -> STC | M18: ='Code-Categories'!C14 -> Approvals & Statutory Charges | N18: =SUMIF($B$7:$B$38,L18,$F$7:$F$38) -> 0
L19: ='Code-Categories'!B15 -> PTC | M19: ='Code-Categories'!C15 -> Petty Cash / Running Expenses | N19: =SUMIF($B$7:$B$38,L19,$F$7:$F$38) -> 0
L20: ='Code-Categories'!B16 -> CON | M20: ='Code-Categories'!C16 -> Contingency | N20: =SUMIF($B$7:$B$38,L20,$F$7:$F$38) -> 0
B39: Total: | F39: =SUM(F7:F38) -> 10134956 | H39: =SUM(H7:H38) -> 503621.3

Sheet 04-Payment Certificate Tracker
B2: Project Name : | C2: Majorda Villa | G2: PROJECT CASHFLOW TRACKER
B3: Client : | C3: Mr. Sanjay Rao
B4: Date : | C4: ='03-Work Order Tracker'!C4 -> 46026
B6: CODE | C6: Vendor | D6: PC Refn | E6: PC Date | F6: PC Value | G6: Payment Value | H6: Payment Date | J6: CODE | L6: Total Value
B7: ='03-Work Order Tracker'!B7 -> CIV | C7: ='03-Work Order Tracker'!C7 -> SS Construction | D7: TAC_PC_25_003 | E7: 46026 | F7: 35000 | G7: 35000 | H7: 46021 | J7: ='Code-Categories'!B3 -> CIV | K7: ='Code-Categories'!C3 -> Civil Works | L7: =SUMIF($B$7:$B$53,J7,$F$7:$F$53) -> 1535000
B8: ='03-Work Order Tracker'!B8 -> ELC | C8: ='03-Work Order Tracker'!C8 -> Suraj Electrician | D8: TAC_PC_25_004 | E8: 46019 | F8: 13530 | G8: =F8 -> 13530 | H8: =H7 -> 46021 | J8: ='Code-Categories'!B4 -> PLB | K8: ='Code-Categories'!C4 -> Plumbing Works | L8: =SUMIF($B$7:$B$53,J8,$F$7:$F$53) -> 0
B9: PRF | C9: Third Angle Concepts | D9: TAC_PC_25_005 | E9: 46019 | F9: 140000 | G9: 140000 | J9: ='Code-Categories'!B5 -> ELC | K9: ='Code-Categories'!C5 -> Electrical Works | L9: =SUMIF($B$7:$B$53,J9,$F$7:$F$53) -> 13530
B10: PRF | C10: CDSP Global | D10: TAC_PC_25_006 | E10: 46082 | F10: 16520 | J10: ='Code-Categories'!B6 -> DWG | K10: ='Code-Categories'!C6 -> Doors, Windows & Glazing | L10: =SUMIF($B$7:$B$53,J10,$F$7:$F$53) -> 0
B11: CIV | C11: Rajesh Construction | D11: TAC_PC_25_007 | E11: 46082 | F11: 1500000 | J11: ='Code-Categories'!B7 -> SWP | K11: ='Code-Categories'!C7 -> Swimming Pool Works | L11: =SUMIF($B$7:$B$53,J11,$F$7:$F$53) -> 0
B12: PRF | C12: Third Angle Concepts | D12: TAC_PC_25_008 | E12: 46090 | F12: 140000 | J12: ='Code-Categories'!B8 -> HVC | K12: ='Code-Categories'!C8 -> HVAC / Air Conditioning | L12: =SUMIF($B$7:$B$53,J12,$F$7:$F$53) -> 0
J13: ='Code-Categories'!B9 -> FIN | K13: ='Code-Categories'!C9 -> Finishing Works | L13: =SUMIF($B$7:$B$53,J13,$F$7:$F$53) -> 0
J14: ='Code-Categories'!B10 -> LAN | K14: ='Code-Categories'!C10 -> Landscapping & External Works | L14: =SUMIF($B$7:$B$53,J14,$F$7:$F$53) -> 0
J15: ='Code-Categories'!B11 -> FAB | K15: ='Code-Categories'!C11 -> Metal & Steel Fabrication | L15: =SUMIF($B$7:$B$53,J15,$F$7:$F$53) -> 0
J16: ='Code-Categories'!B12 -> CSA | K16: ='Code-Categories'!C12 -> Client Supplied Assets | L16: =SUMIF($B$7:$B$53,J16,$F$7:$F$53) -> 0
J17: ='Code-Categories'!B13 -> PRF | K17: ='Code-Categories'!C13 -> Professional Fees | L17: =SUMIF($B$7:$B$53,J17,$F$7:$F$53) -> 296520
J18: ='Code-Categories'!B14 -> STC | K18: ='Code-Categories'!C14 -> Approvals & Statutory Charges | L18: =SUMIF($B$7:$B$53,J18,$F$7:$F$53) -> 0
J19: ='Code-Categories'!B15 -> PTC | K19: ='Code-Categories'!C15 -> Petty Cash / Running Expenses | L19: =SUMIF($B$7:$B$53,J19,$F$7:$F$53) -> 0
J20: ='Code-Categories'!B16 -> CON | K20: ='Code-Categories'!C16 -> Contingency | L20: =SUMIF($B$7:$B$53,J20,$F$7:$F$53) -> 0
B54: Total: | G54: =SUM(G7:G53) -> 188530

Sheet 05-PMC Commercials
B2: Project Name : | C2: Majorda Villa | G2: PMC COMMERCIALS
B3: Client : | C3: Mr. Sanjay Rao
B4: Date : | C4: ='03-Work Order Tracker'!C4 -> 46026
B5: PMC Retainer/Month : | C5: 140000
B8: PC Issue Date | C8: PC Refn | D8: Payment Date | E8: Description | F8: Amount | G8: TDS | H8: Amount Received
B9: 0 | C9: 0 | D9: 45962 | E9: 50% Advance Dec-25 | F9: 70000 | G9: =F9*10% -> 7000 | H9: =F9-G9 -> 63000
B10: 46019 | C10: TAC_PC_25_005 | E10: 50% Bal Dec-25 + 50% Adv Jan -26 | F10: 140000
B56: Total: | G56: =SUM(G9:G55) -> 7000

Sheet 06-Petty Cash Tracker
B2: Project Name : | C2: Majorda Villa | D2: PETTY CASH REGISTER
B3: Client : | C3: Mr. Sanjay Rao
B4: Date : | C4: ='03-Work Order Tracker'!C4 -> 46026
B6: Total Received: | C6: =D11 -> 25000
B7: Total Expenses: | C7: =-SUM(D19:D23) -> 81300
B8: Balance Available : | C8: =C6-C7 -> -56300
B10: Date | C10: Description | D10: Amount | E10: Bill / Invoice
B11: 46000 | C11: Received from Mr. Sanjay | D11: 25000
B12: 46001 | C12: Received from Mr. Sanjay | D12: 60000
B13: 46005 | C13: Assistant Engr (Unofficial) | D13: -45000
B14: 46005 | C14: File Procession (Unofficial) | D14: -15000
B15: 46017 | C15: Lineman (Unofficial) | D15: -15000
B16: 46017 | C16: Meter Box | D16: -3800 | E16: Tax Invoice
B19: 46003 | C19: Electricity Connection Fees | D19: -2500 | E19: Pending
B20: 46007 | C20: File Procession (Unofficial) | D20: -15000 | E20: Cash
B21: 46007 | C21: Assistant Engr (Unofficial) | D21: -40000 | E21: Cash
B22: 46017 | C22: Meter Box | D22: -3800 | E22: Tax Invoice
B23: 46017 | C23: UG Cabling (Unofficial) | D23: -20000 | E23: Cash

Sheet 07-CSA
B2: Project Name : | C2: Majorda Villa | E2: ASSET MANAGEMENT REGISTER
B3: Client : | C3: Mr. Sanjay Rao
B4: Date :
B6: CODE | C6: WO Refn | D6: Description | E6: Value | F6: Received Date
B7: CSA

Sheet Code-Categories
B2: CODE | C2: Category | D2: Inclusion | E2: Exclusion to CSA (Client Supplied Appliances)
A3: 1 | B3: CIV | C3: Civil Works | D3: Excavation, RCC, PCC, masonry, plastering, waterproofing, compound wall, all Grey Works
A4: 2 | B4: PLB | C4: Plumbing Works | D4: Piping, valves, traps, drainage, pump-room piping, STP Setup, Chambers, Storm Drain, Geyser Piping and Fixing of final sanitaryware, steam, sauna, jacuzzi, geyser fixtures | E4: Sanitaryware, faucets, shower sets, pumps.
A5: 3 | B5: ELC | C5: Electrical Works | D5: Conduits, wiring, DBs, breakers, earthing, CCTV, Home Automation, DG Setup, Invertor Setup, Internet Setup, Solar Works and Fixing of all type final fixtures. | E5: Lights, fans, switches, chandeliers.
A6: 4 | B6: DWG | C6: Doors, Windows & Glazing | D6: External Aluminum/UPVC, Main doors, skylights, facade glazing, External Envelope Closure. | E6: Loose Furnitures, Special Lights
A7: 5 | B7: SWP | C7: Swimming Pool Works | D7: Related to Swimming Pool, Waterproofing, Tiling, Pool Light Fixing, Complete Pool Plumbing & Electricals, Pumps, Heaters | E7: AC indoor/outdoor units.
A8: 6 | B8: HVC | C8: HVAC / Air Conditioning | D8: Copper piping, drain lines, insulation and fixing of final units internal and external. | E8: Tile, Stone, Pavers, Roofing Tile, Decorative lights, mirrors, loose décor.
A9: 7 | B9: FIN | C9: Finishing Works | D9: Internal Doors, Windows, Glazing, Flooring, Tiling, Painting (Int & Ext), False ceiling, Wardrobes, kitchen, vanities, fixed furniture. | E9: Loose furniture (sofas, beds, dining).
A10: 8 | B10: LAN | C10: Landscapping & External Works | D10: Greenscaping, Plants, turf, irrigation, pavers, decks. | E10: Garden lights, outdoor furniture.
A11: 9 | B11: FAB | C11: Metal & Steel Fabrication | D11: Railings, gate fabrication, structural framing for roofing, installation of roofing tiles, framing for jali walls, installation of jali wall, steel brackets, platforms, and structural steel elements. | E11: Specialized ornamental items (if client-supplied).
A12: 9 | B12: CSA | C12: Client Supplied Assets | D12: Sanitory Fixtures, light fixtures, HVAC Units, Pumps, DG Unit, all type of appliances, loose furniture, décor, Sofa, Bed, Table, Cabinet, Curtains, Rugs, Cushions, | E12: CCTV cameras, smart locks, automation gadgets.
A13: 10 | B13: PRF | C13: Professional Fees | D13: Architect, Engineers, Consultants, PMC, CA, Security Guards.
A14: 11 | B14: STC | C14: Approvals & Statutory Charges | D14: Govt/Panchayat Permissions, licenses, NOCs, utility connections.
A15: 12 | B15: PTC | C15: Petty Cash / Running Expenses | D15: Drinking Water, Water Tankers, Chairs, stationery, extension boards, Health compliant activities
A16: 13 | B16: CON | C16: Contingency | D16: Buffer for variations & unforeseen items.

Sheet Baseline Budget
D2: Baseline Budget
E3: % | F3: Budget
A4: 1 | B4: CIV | C4: Civil Works | D4: Excavation, RCC, PCC, masonry, plastering, waterproofing, compound wall, all Grey Works | E4: 0.21 | F4: 15000000
A5: 2 | B5: PLB | C5: Plumbing Works | D5: Piping, valves, traps, drainage, pump-room piping, STP Setup, Chambers, Storm Drain, Geyser Piping and Fixing of final sanitaryware, steam, sauna, jacuzzi, geyser fixtures | E5: 0.07 | F5: 5000000
A6: 3 | B6: ELC | C6: Electrical Works | D6: Conduits, wiring, DBs, breakers, earthing, CCTV, Home Automation, DG Setup, Invertor Setup, Internet Setup, Solar Works and Fixing of all type final fixtures. | E6: 0.07 | F6: 5000000
A7: 4 | B7: DWG | C7: Doors, Windows & Glazing | D7: External Aluminum/UPVC, Main doors, skylights, facade glazing, External Envelope Closure. | E7: 11 | F7: 8000000
A8: 5 | B8: SWP | C8: Swimming Pool Works | D8: Related to Swimming Pool, Waterproofing, Tiling, Pool Light Fixing, Complete Pool Plumbing & Electricals, Pumps, Heaters | E8: 0.02 | F8: 1200000
A9: 6 | B9: HVC | C9: HVAC / Air Conditioning | D9: Copper piping, drain lines, insulation and fixing of final units internal and external. | E9: 0.04 | F9: 3000000
A10: 7 | B10: FIN | C10: Finishing Works | D10: Internal Doors, Windows, Glazing, Flooring, Tiling, Painting (Int & Ext), False ceiling, Wardrobes, kitchen, vanities, fixed furniture. | E10: 0.17 | F10: 12000000
A11: 8 | B11: LAN | C11: Landscapping & External Works | D11: Greenscaping, Plants, turf, irrigation, pavers, decks. | E11: 0.03 | F11: 2000000
A12: 9 | B12: CSA | C12: Client Supplied Assets | D12: Sanitory Fixtures, light fixtures, HVAC Units, Pumps, DG Unit, all type of appliances, loose furniture, décor, Sofa, Bed, Table, Cabinet, Curtains, Rugs, Cushions, | E12: 0.11 | F12: 8000000
A13: 10 | B13: PRF | C13: Professional Fees | D13: Architect, Engineers, Consultants, PMC, CA, Security Guards. | E13: 0.07 | F13: 5000000
A14: 11 | B14: STC | C14: Approvals & Statutory Charges | D14: Govt/Panchayat Permissions, licenses, NOCs, utility connections. | E14: 0.02 | F14: 1200000
A15: 12 | B15: PTC | C15: Petty Cash / Running Expenses | D15: Drinking Water, Water Tankers, Chairs, stationery, extension boards, Health compliant activities | E15: 0.03 | F15: =100000*18 -> 1800000
A16: 13 | B16: CON | C16: Contingency | D16: Buffer for variations & unforeseen items. | E16: 0.04 | F16: 2800000
F17: =SUM(F4:F16) -> 70000000
B18: Code | C18: Budget
B19: CIV | C19: =F4 -> 15000000
B20: PLB | C20: =F5 -> 5000000
B21: ELC | C21: =F6 -> 5000000
B22: DWG | C22: =F7 -> 8000000
B23: SWP | C23: =F8 -> 1200000
B24: HVC | C24: =F9 -> 3000000
B25: FIN | C25: =F10 -> 12000000
B26: LAN | C26: =F11 -> 2000000
B27: CSA | C27: =F12 -> 8000000
B28: PRF | C28: =F13 -> 5000000
B29: STC | C29: =F14 -> 1200000
B30: PTC | C30: =F15 -> 1800000
B31: CON | C31: =F16 -> 2800000
